pchem_framework/__init__.py
pchem_framework/calculations/__init__.py
pchem_framework/calculations/concentration.py
pchem_framework/calculations/kinetics.py
pchem_framework/calculations/molar_mass.py
pchem_framework/calculations/ph.py
pchem_framework/calculations/stoichiometry.py
pchem_framework/calculations/thermodynamics.py
pchem_framework/data_handling/__init__.py
pchem_framework/data_handling/data_analysis.py
pchem_framework/data_handling/file_io.py
pchem_framework/data_handling/plotting.py
pchem_framework/data_handling/unit_conversion.py
pchem_framework-0.1.0.dist-info/LICENSE
pchem_framework-0.1.0.dist-info/METADATA
pchem_framework-0.1.0.dist-info/WHEEL
pchem_framework-0.1.0.dist-info/top_level.txt
pchem_framework-0.1.0.dist-info/RECORD
