Metadata-Version: 2.2
Name: pchem-framework
Version: 0.1.0
Summary: Practical chemistry calculations and data handling framework
Home-page: https://github.com/somkietacode/pchem-framework
Author: Ouedraogo Somkieta
Author-email: s.r.a.ouedraogo@gmail.com
Classifier: Programming Language :: Python :: 3
Classifier: License :: OSI Approved :: MIT License
Classifier: Operating System :: OS Independent
Classifier: Topic :: Scientific/Engineering :: Chemistry
Classifier: Intended Audience :: Science/Research
Classifier: Intended Audience :: Education
Requires-Python: >=3.8
License-File: LICENSE
Requires-Dist: numpy>=1.21.0
Requires-Dist: pandas>=1.3.0
Requires-Dist: matplotlib>=3.4.0
Requires-Dist: pint>=0.18
Dynamic: author
Dynamic: author-email
Dynamic: classifier
Dynamic: description
Dynamic: description-content-type
Dynamic: home-page
Dynamic: requires-dist
Dynamic: requires-python
Dynamic: summary
